villaInvDatabase/None.py
villaInvDatabase/__init__.py
villaInvDatabase/_nbdev.py
villaInvDatabase/database.py
villaInvDatabase/database2.py
villaInvDatabase/helper.py
villaInvDatabase/query.py
villaInvDatabase/s3.py
villaInvDatabase/update.py
villaInvDatabase-0.0.40.dist-info/LICENSE
villaInvDatabase-0.0.40.dist-info/METADATA
villaInvDatabase-0.0.40.dist-info/WHEEL
villaInvDatabase-0.0.40.dist-info/entry_points.txt
villaInvDatabase-0.0.40.dist-info/top_level.txt
villaInvDatabase-0.0.40.dist-info/RECORD
