Metadata-Version: 2.1
Name: villaInvDatabase
Version: 0.0.40
Summary: inventory database management functions
Home-page: https://github.com/tenxor/villaInvDatabase/tree/master/
Author: Nic Wanavit
Author-email: nwanavit@hatari.cc
License: Apache Software License 2.0
Keywords: inv database
Platform: UNKNOWN
Classifier: Development Status :: 3 - Alpha
Classifier: Intended Audience :: Developers
Classifier: License :: OSI Approved :: Apache Software License
Classifier: Natural Language :: English
Classifier: Programming Language :: Python :: 3.6
Classifier: Programming Language :: Python :: 3.7
Classifier: Programming Language :: Python :: 3.8
Requires-Python: >=3.6
Requires-Dist: awsSchema
Requires-Dist: boto3
Requires-Dist: pandas
Requires-Dist: pynamodb-dax
Requires-Dist: s3bz
Requires-Dist: lambdasdk
